MIRACLEpy/__init__.py
MIRACLEpy/length.py
MIRACLEpy/main.py
MIRACLEpy/model.py
MIRACLEpy/paras.py
MIRACLEpy/statistics.py
MIRACLEpy/units.py
MIRACLEpy/Data/Invariable_Microsatellite_information.bed
MIRACLEpy/Data/Lengthlist_Reference_normal.txt
MIRACLEpy/Data/Training_data.txt
MIRACLEpy-0.1.dist-info/LICENSE
MIRACLEpy-0.1.dist-info/METADATA
MIRACLEpy-0.1.dist-info/WHEEL
MIRACLEpy-0.1.dist-info/entry_points.txt
MIRACLEpy-0.1.dist-info/top_level.txt
MIRACLEpy-0.1.dist-info/RECORD
