Metadata-Version: 2.1
Name: MIRACLEpy
Version: 0.1
Summary: Microsatellite Instability (MSI) detection with RNA sequencing data.
Home-page: https://github.com/JinWookArgon/MIRACLEpy
Author: Jin-Wook et al.
Author-email: argon502@snu.ac.kr
License: MIT License
Requires-Python: >=3.6
License-File: LICENSE
Requires-Dist: pandas >=0.25
Requires-Dist: pysam >=0.15
Requires-Dist: scikit-learn >=0.21
